geneflow/__init__.py
geneflow/__main__.py
geneflow/app_installer.py
geneflow/config.py
geneflow/data.py
geneflow/data_manager.py
geneflow/definition.py
geneflow/environment.py
geneflow/log.py
geneflow/shell_wrapper.py
geneflow/stageable_data.py
geneflow/template_compiler.py
geneflow/uri_parser.py
geneflow/workflow.py
geneflow/workflow_dag.py
geneflow/workflow_input.py
geneflow/workflow_installer.py
geneflow/workflow_step.py
geneflow/cli/__init__.py
geneflow/cli/add_apps.py
geneflow/cli/add_workflows.py
geneflow/cli/common.py
geneflow/cli/help.py
geneflow/cli/init_db.py
geneflow/cli/install_workflow.py
geneflow/cli/make_app.py
geneflow/cli/migrate_db.py
geneflow/cli/run.py
geneflow/cli/run_pending.py
geneflow/data/migrations/.gitignore
geneflow/data/sql/geneflow-sqlite.sql
geneflow/data/sql/geneflow.sql
geneflow/data/templates/test.sh.j2
geneflow/data/templates/wrapper-script.sh.j2
geneflow/extend/__init__.py
geneflow/extend/contexts.py
geneflow/extend/data_manager_contexts.py
geneflow/extend/gridengine_step.py
geneflow/extend/gridengine_workflow.py
geneflow/extend/local_step.py
geneflow/extend/local_workflow.py
geneflow/extend/slurm_step.py
geneflow/extend/slurm_workflow.py
geneflow3-3.0.0a1.dist-info/LICENSE
geneflow3-3.0.0a1.dist-info/METADATA
geneflow3-3.0.0a1.dist-info/WHEEL
geneflow3-3.0.0a1.dist-info/entry_points.txt
geneflow3-3.0.0a1.dist-info/top_level.txt
geneflow3-3.0.0a1.dist-info/RECORD
