Metadata-Version: 2.1
Name: geneflow3
Version: 3.0.0a1
Summary: A light-weight, extendable workflow engine for scientific computing.
Home-page: https://github.com/jhphan/geneflow
Author: John Phan
Author-email: jhphan@gmail.com
License: Apache 2.0
Keywords: workflow bioinformatics
Platform: UNKNOWN
Classifier: Development Status :: 5 - Production/Stable
Classifier: Intended Audience :: Science/Research
Classifier: Intended Audience :: Developers
Classifier: Operating System :: POSIX :: BSD
Classifier: Programming Language :: Python :: 3
Classifier: Programming Language :: Python :: 3.5
Classifier: Programming Language :: Python :: 3.6
Classifier: Programming Language :: Python :: 3.7
Classifier: Programming Language :: Python :: 3.8
Classifier: Programming Language :: Python :: 3 :: Only
Classifier: Topic :: Scientific/Engineering :: Bio-Informatics
Requires-Python: >=3.5.*
Requires-Dist: GitPython (~=2.1.11)
Requires-Dist: Jinja2 (>=2.10.1)
Requires-Dist: PyMySQL (>=0.8.0)
Requires-Dist: PyYAML (>=5.3.1)
Requires-Dist: cerberus (~=1.2)
Requires-Dist: networkx (>=2.1)
Requires-Dist: pytest (>=2.7.0)
Requires-Dist: python-slugify (>=1.2.5)
Requires-Dist: regex (>=2020.11.13)
Requires-Dist: requests (>=2.23.0)
Requires-Dist: sqlalchemy (>=1.3.16)
Requires-Dist: wcmatch (~=7.1)
Requires-Dist: yoyo-migrations (>=5.0.5)
Provides-Extra: hpc
Requires-Dist: drmaa ; extra == 'hpc'
